google_photos_archiver/__init__.py
google_photos_archiver/album.py
google_photos_archiver/archivers.py
google_photos_archiver/cli.py
google_photos_archiver/cli_utils.py
google_photos_archiver/filters.py
google_photos_archiver/media_item.py
google_photos_archiver/media_item_archiver.py
google_photos_archiver/media_item_recorder.py
google_photos_archiver/oauth_handler.py
google_photos_archiver/rest_client.py
google_photos_archiver-0.2.1.dist-info/entry_points.txt
google_photos_archiver-0.2.1.dist-info/LICENSE
google_photos_archiver-0.2.1.dist-info/WHEEL
google_photos_archiver-0.2.1.dist-info/METADATA
google_photos_archiver-0.2.1.dist-info/RECORD
