Metadata-Version: 2.1
Name: google-photos-archiver
Version: 0.2.1
Summary: Archives the contents of your Google Photos library to disk
Home-page: https://github.com/scottx611x/google-photos-archiver
License: MIT
Keywords: Google Photos,Photo Backup,Media Arcvhival,Data Backup
Author: Scott Ouellette
Author-email: scottx611x@gmail.com
Maintainer: Scott Ouellette
Maintainer-email: scottx611x@gmail.com
Requires-Python: >=3.8.0,<4.0.0
Classifier: License :: OSI Approved :: MIT License
Classifier: Programming Language :: Python :: 3
Classifier: Programming Language :: Python :: 3.8
Requires-Dist: click (==7.1.2)
Requires-Dist: google-auth-oauthlib (>=0.4.2,<0.5.0)
Requires-Dist: requests (==2.25.1)
